biolink_mcp/__init__.py
biolink_mcp/server.py
biolink_mcp-0.1.0.dist-info/METADATA
biolink_mcp-0.1.0.dist-info/WHEEL
biolink_mcp-0.1.0.dist-info/entry_points.txt
biolink_mcp-0.1.0.dist-info/RECORD
