Metadata-Version: 2.4
Name: biolink-mcp
Version: 0.1.0
Summary: MCP server for Biolink Model Toolkit
Project-URL: Homepage, https://github.com/cbizon/RoboMCP
Project-URL: Repository, https://github.com/cbizon/RoboMCP
Project-URL: Issues, https://github.com/cbizon/RoboMCP/issues
Author: Chris Bizon
License: MIT
Keywords: biolink,biomedical,knowledge-graph,mcp,translator
Classifier: Development Status :: 4 - Beta
Classifier: Intended Audience :: Developers
Classifier: Intended Audience :: Science/Research
Classifier: License :: OSI Approved :: MIT License
Classifier: Programming Language :: Python :: 3
Classifier: Programming Language :: Python :: 3.10
Classifier: Programming Language :: Python :: 3.11
Classifier: Programming Language :: Python :: 3.12
Classifier: Topic :: Scientific/Engineering :: Bio-Informatics
Requires-Python: >=3.10
Requires-Dist: bmt>=1.0.0
Requires-Dist: fastmcp>=0.1.0
